MANIFEST.in
README.md
requirements.txt
setup.cfg
setup.py
ckerl/__init__.py
ckerl/conv.c
ckerl/conv.pyx
ckerl/kerl.c
ckerl/kerl.pyx
ckerl.egg-info/PKG-INFO
ckerl.egg-info/SOURCES.txt
ckerl.egg-info/dependency_links.txt
ckerl.egg-info/requires.txt
ckerl.egg-info/top_level.txt