Metadata-Version: 1.0
Name: ckerl
Version: 1.0.0
Summary: Cython implementation of Kerl
Home-page: https://github.com/scottbelden/ckerl
Author: Scott Belden
Author-email: scottabelden@gmail.com
License: MIT
Platform: UNKNOWN
